wtu_mlflow_triton_plugin/__init__.py
wtu_mlflow_triton_plugin/config.py
wtu_mlflow_triton_plugin/model_config.py
wtu_mlflow_triton_plugin/plugin.py
wtu_mlflow_triton_plugin/py.typed
wtu_mlflow_triton_plugin/storage.py
wtu_mlflow_triton_plugin/auth/__init__.py
wtu_mlflow_triton_plugin/auth/client.py
wtu_mlflow_triton_plugin/auth/credentials.py
wtu_mlflow_triton_plugin/cli/__init__.py
wtu_mlflow_triton_plugin/cli/main.py
wtu_mlflow_triton_plugin/function/__init__.py
wtu_mlflow_triton_plugin/function/builder.py
wtu_mlflow_triton_plugin/function/decorator.py
wtu_mlflow_triton_plugin/function/models.py
wtu_mlflow_triton_plugin/function/validator.py
wtu_mlflow_triton_plugin/function/venv_manager.py
wtu_mlflow_triton_plugin-0.0.17.dist-info/METADATA
wtu_mlflow_triton_plugin-0.0.17.dist-info/WHEEL
wtu_mlflow_triton_plugin-0.0.17.dist-info/entry_points.txt
wtu_mlflow_triton_plugin-0.0.17.dist-info/licenses/LICENSE
wtu_mlflow_triton_plugin-0.0.17.dist-info/RECORD
