Metadata-Version: 2.4
Name: wtu-mlflow-triton-plugin
Version: 0.0.17
Summary: MLflow plugin for Triton Inference Server with secure Python function execution
Project-URL: Homepage, https://github.com/hbjs/w-train-utils-mlflow-triton-plugin
Project-URL: Bug Tracker, https://github.com/hbjs/w-train-utils-mlflow-triton-plugin/issues
Project-URL: Documentation, https://github.com/hbjs/w-train-utils-mlflow-triton-plugin#readme
Author-email: hbjs <hbjs97@naver.com>
License: MIT
License-File: LICENSE
Keywords: deployment,inference,machine-learning,mlflow,triton
Classifier: Development Status :: 3 - Alpha
Classifier: Intended Audience :: Developers
Classifier: License :: OSI Approved :: MIT License
Classifier: Programming Language :: Python :: 3
Classifier: Programming Language :: Python :: 3.9
Classifier: Programming Language :: Python :: 3.10
Classifier: Programming Language :: Python :: 3.11
Classifier: Programming Language :: Python :: 3.12
Classifier: Topic :: Scientific/Engineering :: Artificial Intelligence
Classifier: Topic :: Software Development :: Libraries :: Python Modules
Requires-Python: >=3.9
Requires-Dist: boto3>=1.24.0
Requires-Dist: cryptography>=45.0.4
Requires-Dist: mlflow==1.30.1
Requires-Dist: numpy>=1.26.4
Requires-Dist: requests==2.32.4
Requires-Dist: tqdm==4.67.1
Requires-Dist: tritonclient[grpc,http]>=2.36.0
